ukaddress/__init__.py
ukaddress/generator.py
ukaddress/parser.py
ukaddress-0.1.0.dist-info/licenses/LICENSE
ukaddress-0.1.0.dist-info/METADATA
ukaddress-0.1.0.dist-info/WHEEL
ukaddress-0.1.0.dist-info/top_level.txt
ukaddress-0.1.0.dist-info/RECORD
